cek/__init__.py
cek/clova.py
cek/core.py
cek/version.py
clova_cek_sdk-1.0.0.dist-info/METADATA
clova_cek_sdk-1.0.0.dist-info/RECORD
clova_cek_sdk-1.0.0.dist-info/WHEEL
clova_cek_sdk-1.0.0.dist-info/top_level.txt
