Metadata-Version: 2.1
Name: clova-cek-sdk
Version: 1.0.0
Summary: Python Micro SDK for the Clova Extension Kit
Home-page: https://github.com/line/clova-cek-sdk-python/
Author: LINE Corp.
Author-email: dl_pypi@linecorp.com
License: Apache License 2.0
Platform: UNKNOWN
Classifier: Development Status :: 5 - Production/Stable
Classifier: License :: OSI Approved :: Apache Software License
Classifier: Intended Audience :: Developers
Classifier: Programming Language :: Python
Classifier: Programming Language :: Python :: 2
Classifier: Programming Language :: Python :: 2.7
Classifier: Programming Language :: Python :: 3
Classifier: Programming Language :: Python :: 3.3
Classifier: Programming Language :: Python :: 3.4
Classifier: Programming Language :: Python :: 3.5
Classifier: Programming Language :: Python :: 3.6
Classifier: Topic :: Software Development
Provides-Extra: docs
Requires-Dist: cryptography
Provides-Extra: docs
Requires-Dist: sphinx; extra == 'docs'
Requires-Dist: sphinx-rtd-theme; extra == 'docs'
Requires-Dist: sphinxcontrib-versioning; extra == 'docs'
